<?xml version="1.0" encoding="UTF-8" standalone="yes"?>
<template encoding-version="1.2">
    <description></description>
    <groupId>fc3410cb-016c-1000-2b16-95fa34ee485a</groupId>
    <name>nifi_flow_template_hl7_processing</name>
    <snippet>
        <controllerServices>
            <id>074eb097-7cd1-3f52-0000-000000000000</id>
            <parentGroupId>c5f43f76-207f-3930-0000-000000000000</parentGroupId>
            <bundle>
                <artifact>nifi-MapAttributeNames-nar</artifact>
                <group>nifi.test</group>
                <version>1.0-SNAPSHOT</version>
            </bundle>
            <comments></comments>
            <descriptors>
                <entry>
                    <key>csv-file</key>
                    <value>
                        <name>csv-file</name>
                    </value>
                </entry>
                <entry>
                    <key>csv-format</key>
                    <value>
                        <name>csv-format</name>
                    </value>
                </entry>
                <entry>
                    <key>Character Set</key>
                    <value>
                        <name>Character Set</name>
                    </value>
                </entry>
                <entry>
                    <key>input-attribute-name-column</key>
                    <value>
                        <name>input-attribute-name-column</name>
                    </value>
                </entry>
                <entry>
                    <key>output-lookup-value-column</key>
                    <value>
                        <name>output-lookup-value-column</name>
                    </value>
                </entry>
            </descriptors>
            <name>CSVToMapService</name>
            <persistsState>false</persistsState>
            <properties>
                <entry>
                    <key>csv-file</key>
                    <value>/home/ubuntu/test_files/lookup/mapping.csv</value>
                </entry>
                <entry>
                    <key>csv-format</key>
                    <value>Default</value>
                </entry>
                <entry>
                    <key>Character Set</key>
                    <value>UTF-8</value>
                </entry>
                <entry>
                    <key>input-attribute-name-column</key>
                    <value>input</value>
                </entry>
                <entry>
                    <key>output-lookup-value-column</key>
                    <value>output</value>
                </entry>
            </properties>
            <state>ENABLED</state>
            <type>CSVToMapServicePkg.StandardMyService</type>
        </controllerServices>
        <processors>
            <id>e0fe2cd8-ea99-3428-0000-000000000000</id>
            <parentGroupId>c5f43f76-207f-3930-0000-000000000000</parentGroupId>
            <position>
                <x>0.0</x>
                <y>0.0</y>
            </position>
            <bundle>
                <artifact>nifi-MapAttributeNames-nar</artifact>
                <group>nifi.test</group>
                <version>1.0-SNAPSHOT</version>
            </bundle>
            <config>
                <bulletinLevel>WARN</bulletinLevel>
                <comments></comments>
                <concurrentlySchedulableTaskCount>1</concurrentlySchedulableTaskCount>
                <descriptors>
                    <entry>
                        <key>CSVToMapService</key>
                        <value>
                            <identifiesControllerService>CSVToMapServicePkg.MyService</identifiesControllerService>
                            <name>CSVToMapService</name>
                        </value>
                    </entry>
                </descriptors>
                <executionNode>ALL</executionNode>
                <lossTolerant>false</lossTolerant>
                <penaltyDuration>30 sec</penaltyDuration>
                <properties>
                    <entry>
                        <key>CSVToMapService</key>
                        <value>074eb097-7cd1-3f52-0000-000000000000</value>
                    </entry>
                </properties>
                <runDurationMillis>0</runDurationMillis>
                <schedulingPeriod>0 sec</schedulingPeriod>
                <schedulingStrategy>TIMER_DRIVEN</schedulingStrategy>
                <yieldDuration>1 sec</yieldDuration>
            </config>
            <executionNodeRestricted>false</executionNodeRestricted>
            <name>MapAttributeNames</name>
            <relationships>
                <autoTerminate>true</autoTerminate>
                <name>failure</name>
            </relationships>
            <relationships>
                <autoTerminate>false</autoTerminate>
                <name>success</name>
            </relationships>
            <state>STOPPED</state>
            <style/>
            <type>MapAttributeNamesPkg.MyProcessor</type>
        </processors>
    </snippet>
    <timestamp>11/08/2019 15:28:08 CET</timestamp>
</template>
